extoracle/__init__.py
extoracle/extoracle.py
extoracle/utils.py
extoracle/bin/__init__.py
extoracle/bin/cmd.py
extoracle-0.1.dist-info/LICENSE
extoracle-0.1.dist-info/METADATA
extoracle-0.1.dist-info/WHEEL
extoracle-0.1.dist-info/entry_points.txt
extoracle-0.1.dist-info/top_level.txt
extoracle-0.1.dist-info/RECORD
