Metadata-Version: 2.1
Name: extoracle
Version: 0.1
Summary: Ext-Oracle Summarization
Home-page: UNKNOWN
License: UNKNOWN
Project-URL: Source, https://github.com/pltrdy/extoracle_summarization/
Platform: UNKNOWN
Requires-Dist: rouge (>=1.0.0rc1)
